{
    "configurations": [
        {
            "name": "Win32 DEBUG",
            "includePath": [
                "${workspaceFolder}/Engine/**",
                "${workspaceFolder}/libenjoy-master/**",
                "${workspaceFolder}/Game/**"
            ],
            "defines": [
                "_DEBUG",
                "UNICODE",
                "_UNICODE"
            ],
            "windowsSdkVersion": "10.0.18362.0",
            "compilerPath": "E:/msys64/mingw64/bin/gcc",
            "cStandard": "c11",
            "cppStandard": "c++11",
            "intelliSenseMode": "windows-gcc-x64",
            "compilerArgs": [],
            "configurationProvider": "ms-vscode.makefile-tools"
        }
    ],
    "version": 4
}